Metadata-Version: 1.0
Name: GaussianBionomialDistributions
Version: 0.1
Summary: Gaussian distributions Binomial Distibutions
Home-page: UNKNOWN
Author: UNKNOWN
Author-email: UNKNOWN
License: UNKNOWN
Platform: UNKNOWN
